{
    "$id": "https://data.landsofhope.com/schemas/v1/chat/chat-mention.json",
    "title": "ChatMention",
    "type": "object",
    "additionalProperties": false,
    "properties": {
        "$type": {
            "const": "/v1/chat/chat-mention"
        },
        "target": {
            "$ref": "/schemas/v1/chat/chat-participant-id.json"
        },
        "profile": {
            "$ref": "/schemas/v1/characters/appearance-profile.json"
        }
    },
    "required": [
        "$type",
        "target",
        "profile"
    ]
}