{
    "name": {
        "en": "Fighter"
    },
    "desc": {
        "en": "Throughout history we have known many wars each one tainted by the blood of the fallen souls who died defending their \"point of view\", the Fighter profession would in most wars be the first to die or the last person standing at the end of the conflict. They are skilled expertly in most one handed weapons to the point where they can dual wield and still be effective."
    },
    "skills": {
        "taunting": 5,
        "daggers": 5,
        "swords": 5,
        "axes": 5,
        "maces": 5,
        "fists": 5,
        "dual-wielding": 5,
        "armor": 5,
        "attack-power": 5
    },
    "evo": {}
}